shellml/__init__.py
shellml/main.py
shellml-0.1.1.dist-info/LICENSE
shellml-0.1.1.dist-info/METADATA
shellml-0.1.1.dist-info/WHEEL
shellml-0.1.1.dist-info/top_level.txt
shellml-0.1.1.dist-info/RECORD
