Metadata-Version: 2.1
Name: shellml
Version: 0.1.1
Summary: A texutal interface for monitoring ML experiments in the terminal
Home-page: https://github.com/alberto-rota/shellml
Author: Alberto Rota
Author-email: alberto1.rota@polimi.it
License: GPLv3
Classifier: Programming Language :: Python :: 3
Classifier: License :: OSI Approved :: GNU General Public License v3 (GPLv3)
Classifier: Operating System :: OS Independent
Requires-Python: >=3.6
License-File: LICENSE
Requires-Dist: numpy==2.1.3
Requires-Dist: plotext==5.3.2
Requires-Dist: setuptools==75.1.0
Requires-Dist: textual==0.89.1
